setup.cfg
setup.py
dap/__init__.py
dap.plugins.grib2.egg-info/PKG-INFO
dap.plugins.grib2.egg-info/SOURCES.txt
dap.plugins.grib2.egg-info/dependency_links.txt
dap.plugins.grib2.egg-info/entry_points.txt
dap.plugins.grib2.egg-info/namespace_packages.txt
dap.plugins.grib2.egg-info/paster_plugins.txt
dap.plugins.grib2.egg-info/requires.txt
dap.plugins.grib2.egg-info/top_level.txt
dap.plugins.grib2.egg-info/zip-safe
dap/plugins/__init__.py
dap/plugins/grib2/README.txt
dap/plugins/grib2/__init__.py
dap/plugins/grib2/gdal_test
dap/plugins/grib2/mkinv.py
dap/plugins/grib2/ncep.xml
dap/plugins/grib2/projtest
dap/plugins/grib2/rd_dap
